spherical_inr/__init__.py
spherical_inr/_activation.py
spherical_inr/differentiation.py
spherical_inr/inr.py
spherical_inr/loss.py
spherical_inr/mlp.py
spherical_inr/positional_encoding.py
spherical_inr/rotations.py
spherical_inr/transforms.py
spherical_inr/third_party/locationencoder/gen_sh.py
spherical_inr/third_party/locationencoder/sh.py
spherical_inr-0.4.3.dist-info/licenses/LICENSE
spherical_inr-0.4.3.dist-info/METADATA
spherical_inr-0.4.3.dist-info/WHEEL
spherical_inr-0.4.3.dist-info/top_level.txt
spherical_inr-0.4.3.dist-info/RECORD
