Metadata-Version: 2.4
Name: spherical_inr
Version: 0.4.3
Summary: A package for spherical positional encoding
Home-page: https://github.com/TheoHanon/Spherical-Implicit-Neural-Representation
Author: Theo Hanon
Author-email: Theo Hanon <theo.hanon@student.uclouvain.be>
License: MIT License
Project-URL: Documentation, https://spherical-implicit-neural-representation.readthedocs.io/en/latest/
Project-URL: Source Code, https://github.com/TheoHanon/Spherical-Implicit-Neural-Representation
Classifier: Programming Language :: Python :: 3
Classifier: License :: OSI Approved :: MIT License
Classifier: Operating System :: OS Independent
Requires-Python: >=3.6
License-File: LICENSE
Requires-Dist: torch>=1.7.0
Dynamic: author
Dynamic: home-page
Dynamic: license-file
Dynamic: requires-python
